setup.py
pyparade/__init__.py
pyparade/operations.py
pyparade/test_pyparade.py
pyparade.egg-info/PKG-INFO
pyparade.egg-info/SOURCES.txt
pyparade.egg-info/dependency_links.txt
pyparade.egg-info/top_level.txt
pyparade.egg-info/zip-safe
pyparade/util/__init__.py
pyparade/util/btree.py