Metadata-Version: 1.1
Name: pyparade
Version: 0.1.4
Summary: Python library to parallel process data efficiently
Home-page: http://nilsbreyer.eu/#!projects/pyparade
Author: Nils Breyer
Author-email: mail@nilsbreyer.eu
License: MIT License
Keywords: big data parallel processing
Platform: UNKNOWN
Classifier: License :: OSI Approved :: MIT License
Classifier: Development Status :: 3 - Alpha
Classifier: Environment :: Console
Classifier: Intended Audience :: Information Technology
Classifier: Natural Language :: English
Classifier: Operating System :: MacOS :: MacOS X
Classifier: Operating System :: POSIX :: Linux
Classifier: Programming Language :: Python :: 2.7
